iiif_downgrade/__init__.py
iiif_downgrade/converter/__init__.py
iiif_downgrade/converter/converter.py
iiif_downgrade/iiif_downgrade.py
iiif_downgrade-0.1.3.dist-info/LICENSE
iiif_downgrade-0.1.3.dist-info/METADATA
iiif_downgrade-0.1.3.dist-info/WHEEL
iiif_downgrade-0.1.3.dist-info/entry_points.txt
iiif_downgrade-0.1.3.dist-info/RECORD
