Metadata-Version: 2.1
Name: iiif-downgrade
Version: 0.1.3
Summary: 
Author: Mark Baggett
Author-email: markpbaggett@gmail.com
Requires-Python: >=3.12,<4.0
Classifier: Programming Language :: Python :: 3
Classifier: Programming Language :: Python :: 3.12
Requires-Dist: click (>=8.3.1,<9.0.0)
